elexonapi/__init__.py
elexonapi/datasets.py
elexonapi/download.py
elexonapi/prod-insol-insights-api.json
elexonapi/registry.py
elexonapi-0.1.4.dist-info/METADATA
elexonapi-0.1.4.dist-info/WHEEL
elexonapi-0.1.4.dist-info/top_level.txt
elexonapi-0.1.4.dist-info/RECORD
