Metadata-Version: 2.4
Name: elexonapi
Version: 0.1.4
Summary: Lightweight Python client for the Elexon Insights API.
Author: Imran
License: MIT
Project-URL: Repository, https://github.com/imranmannan/elexonapi
Project-URL: Changelog, https://github.com/imranmannan/elexonapi/blob/main/CHANGELOG.md
Keywords: Elexon,BMRS,Insights,energy,API
Requires-Python: <3.13,>=3.10
Requires-Dist: itables>=2.6.2
Requires-Dist: pandas>=2.3.3
Requires-Dist: requests>=2.32.5
Requires-Dist: tqdm>=4.67.1
